pytorch_types/__init__.py
pytorch_types/numpy.py
pytorch_types/tensor.py
pytorch_types-0.1.0.dist-info/LICENSE
pytorch_types-0.1.0.dist-info/WHEEL
pytorch_types-0.1.0.dist-info/METADATA
pytorch_types-0.1.0.dist-info/RECORD
